ulifdns/__init__.py
ulifdns/ulif.py
UlifTor-1.0.0.dist-info/METADATA
UlifTor-1.0.0.dist-info/WHEEL
UlifTor-1.0.0.dist-info/top_level.txt
UlifTor-1.0.0.dist-info/RECORD
